README.md
setup.py
Matricx/__init__.py
Matricx/matricx.py
Matricx.egg-info/PKG-INFO
Matricx.egg-info/SOURCES.txt
Matricx.egg-info/dependency_links.txt
Matricx.egg-info/not-zip-safe
Matricx.egg-info/top_level.txt