Metadata-Version: 1.0
Name: Matricx
Version: 0.0.1
Summary: Python package to implement basic matrix operations
Home-page: UNKNOWN
Author: Sagnik Mazumder, Sucheta Roy
Author-email: sagnikmazumdar37@gmail.com, sucheta56roy@gmail.com
License: MIT
Platform: UNKNOWN
